{"frameRate":24,"name":"corn","version":"5.5","compatibleVersion":"5.5","armature":[{"type":"Armature","frameRate":24,"name":"Armature","aabb":{"x":-52.5,"y":-139.28,"width":160.05,"height":252.4},"bone":[{"name":"root","transform":{"x":4.5,"y":-1.381}},{"length":10,"name":"L","parent":"root","transform":{"x":3.4673,"y":-94.1721,"skX":-90,"skY":-90,"scX":0.01,"scY":0.01}},{"length":81,"name":"body","parent":"root","transform":{"x":-5.25,"y":92.8,"skX":-86.26,"skY":-86.26}},{"length":10,"name":"L1","parent":"root","transform":{"x":3.4673,"y":-94.1721,"skX":-90,"skY":-90,"scX":0.01,"scY":0.01}},{"length":28,"name":"spray","parent":"root","transform":{"x":57.35,"y":-23,"skX":-90,"skY":-90}},{"length":73,"name":"exclamation","parent":"root","transform":{"x":29.3961,"y":-88.8845,"skX":52,"skY":52,"scX":0.45,"scY":0.45}},{"length":4,"name":"blush","parent":"body","transform":{"x":128.0258,"y":-7.6172,"skX":-3.74,"skY":-3.74}},{"length":15,"name":"hair_2","parent":"body","transform":{"x":183.858,"y":-10.5654,"skX":18.2376,"skY":18.2376}},{"length":9,"name":"mouth","parent":"body","transform":{"x":120.4009,"y":-6.2169,"skX":-3.74,"skY":-3.74}},{"length":7,"name":"eye","parent":"body","transform":{"x":140.3648,"y":-7.4217,"skX":-3.74,"skY":-3.74}},{"length":78,"name":"leaf_1","parent":"body","transform":{"x":-8.7108,"y":7.7848,"skX":-24.5848,"skY":-24.5848}},{"length":10,"name":"hair_1","parent":"body","transform":{"x":182.159,"y":-13.5609,"skX":-19.8,"skY":-19.8}},{"length":17,"name":"hair_3","parent":"body","transform":{"x":183.5023,"y":-10.6423,"skX":-4.0674,"skY":-4.0674}},{"length":14,"name":"leaf_3","parent":"body","transform":{"x":-2.7235,"y":7.3934,"skX":174.6744,"skY":174.6744}},{"length":75,"name":"leaf_2","parent":"body","transform":{"x":-7.3783,"y":3.639,"skX":24.2027,"skY":24.2027}},{"length":15,"name":"spray_2","parent":"spray","transform":{"x":48.3,"y":0.35}},{"length":47,"name":"spray_0","parent":"spray_2","transform":{"x":12.8,"y":-4.1538,"skX":-90,"skY":-90,"scX":0.01,"scY":0.01}}],"slot":[{"name":"body_1","parent":"body"},{"name":"blush","parent":"blush"},{"name":"mouth","parent":"mouth"},{"name":"eye","parent":"eye"},{"name":"hair_3","parent":"hair_3"},{"name":"hair_2","parent":"hair_2"},{"name":"hair_1","parent":"hair_1"},{"name":"leaf_3","parent":"leaf_3"},{"name":"leaf_2","parent":"leaf_2"},{"name":"leaf_1","parent":"leaf_1"},{"name":"spray_0","parent":"spray_0"},{"name":"spray_2","parent":"spray_2","color":{"aM":0}},{"name":"spray_1","parent":"spray","color":{"aM":0}},{"name":"L","parent":"L"},{"name":"L1","parent":"L1"},{"name":"exclamation","parent":"exclamation","color":{"aM":0}}],"skin":[{"slot":[{"name":"L1","display":[{"name":"corn/L","transform":{"x":0.61,"y":0.25,"skX":90,"skY":90}}]},{"name":"exclamation","display":[{"name":"corn/exclamation","transform":{"x":56.52,"y":-0.21,"skX":90,"skY":90}}]},{"name":"body_1","display":[{"name":"corn/body_1","transform":{"x":92.59,"y":-6.3,"skX":86.26,"skY":86.26}},{"name":"corn/body_2","transform":{"x":92.59,"y":-6.3,"skX":86.26,"skY":86.26}}]},{"name":"blush","display":[{"name":"corn/blush","transform":{"x":1.05,"y":2.5,"skX":90,"skY":90}}]},{"name":"mouth","display":[{"name":"corn/mouth_1","transform":{"x":6.25,"y":1.1,"skX":90,"skY":90}},{"name":"corn/mouth_2","transform":{"x":4.61,"y":0.5,"skX":90,"skY":90}},{"name":"corn/mouth_3","transform":{"x":4.61,"y":0.5,"skX":90,"skY":90}}]},{"name":"eye","display":[{"name":"corn/eye_1","transform":{"x":2.75,"y":1.5,"skX":90,"skY":90}},{"name":"corn/eye_2","transform":{"x":2.75,"y":1.5,"skX":90,"skY":90}},{"name":"corn/eye_3","transform":{"x":2.75,"y":1.5,"skX":90,"skY":90}}]},{"name":"hair_3","display":[{"name":"corn/hair_3","transform":{"x":11.34,"y":1.46,"skX":90.33,"skY":90.33}}]},{"name":"hair_2","display":[{"name":"corn/hair_2","transform":{"x":9.49,"y":0.81,"skX":68.02,"skY":68.02}}]},{"name":"hair_1","display":[{"name":"corn/hair_1","transform":{"x":7.79,"y":0.06,"skX":106.06,"skY":106.06}}]},{"name":"leaf_3","display":[{"name":"corn/leaf3","transform":{"x":6.47,"y":1.13,"skX":-88.41,"skY":-88.41}}]},{"name":"leaf_2","display":[{"name":"corn/leaf_2","transform":{"x":58.43,"y":-14.47,"skX":62.06,"skY":62.06}}]},{"name":"leaf_1","display":[{"name":"corn/leaf_1","transform":{"x":74.59,"y":2.24,"skX":110.84,"skY":110.84}}]},{"name":"spray_0","display":[{"name":"corn/spray_0","transform":{"x":49.4,"y":-0.1,"skX":180,"skY":180}}]},{"name":"spray_2","display":[{"name":"corn/spray_3","transform":{"x":8.2,"y":0.3,"skX":90,"skY":90}}]},{"name":"spray_1","display":[{"name":"corn/spray_1","transform":{"x":25,"y":1.15,"skX":90,"skY":90}}]},{"name":"L","display":[{"name":"corn/L","transform":{"x":0.61,"y":0.25,"skX":90,"skY":90}}]}]}],"animation":[{"duration":0,"playTimes":0,"name":"click","slot":[{"name":"mouth","displayFrame":[{"duration":0,"value":2}]},{"name":"eye","displayFrame":[{"duration":0,"value":2}]}]},{"duration":106,"playTimes":0,"name":"usual","bone":[{"name":"spray","translateFrame":[{"duration":49},{"duration":12,"tweenEasing":0,"x":33.89,"y":22.24},{"duration":26,"tweenEasing":0,"y":-21.15},{"duration":10,"tweenEasing":0,"y":-21.15},{"duration":9,"x":2.59,"y":-76.63}],"rotateFrame":[{"duration":49},{"duration":12,"tweenEasing":0,"rotate":-11},{"duration":26,"tweenEasing":0},{"duration":10,"tweenEasing":0},{"duration":9,"rotate":24}]},{"name":"body","scaleFrame":[{"duration":41},{"duration":8,"tweenEasing":0},{"duration":16,"tweenEasing":0,"x":0.95},{"duration":33,"tweenEasing":0,"x":0.95},{"duration":8}]},{"name":"hair_2","translateFrame":[{"duration":24},{"duration":7,"tweenEasing":0},{"tweenEasing":0,"x":13.54,"y":-26.32},{"duration":74}],"rotateFrame":[{"duration":4,"tweenEasing":0},{"duration":4,"tweenEasing":0,"rotate":-17},{"duration":4,"tweenEasing":0,"rotate":-2},{"duration":4,"tweenEasing":0,"rotate":-17},{"duration":4,"tweenEasing":0,"rotate":-2},{"duration":4,"tweenEasing":0,"rotate":-17},{"duration":7,"tweenEasing":0,"rotate":-2},{"duration":36,"tweenEasing":0,"rotate":-46},{"duration":2,"tweenEasing":0},{"duration":2,"tweenEasing":0,"rotate":-17},{"duration":2,"tweenEasing":0,"rotate":-2},{"duration":2,"tweenEasing":0,"rotate":-17},{"duration":2,"tweenEasing":0,"rotate":-2},{"duration":2,"tweenEasing":0,"rotate":-17},{"duration":2,"tweenEasing":0,"rotate":-2},{"duration":2,"tweenEasing":0,"rotate":-17},{"duration":2,"tweenEasing":0,"rotate":-2},{"duration":2,"tweenEasing":0,"rotate":-17},{"duration":3,"tweenEasing":0,"rotate":-2},{"duration":4,"tweenEasing":0,"rotate":-17},{"duration":4,"tweenEasing":0,"rotate":-2},{"duration":4,"tweenEasing":0,"rotate":-17},{"duration":4,"tweenEasing":0,"rotate":-2},{"duration":0}],"scaleFrame":[{"duration":24},{"duration":7,"tweenEasing":0},{"tweenEasing":0,"x":1.15,"y":1.15},{"duration":35,"tweenEasing":0,"x":0.01,"y":0.01},{"duration":16,"tweenEasing":0,"x":0.01,"y":0.01},{"duration":23}]},{"name":"mouth","translateFrame":[{"duration":60},{"duration":3,"tweenEasing":0},{"duration":2,"tweenEasing":0,"x":-0.3,"y":-4.63},{"duration":2,"tweenEasing":0,"x":0.27,"y":4.13},{"duration":2,"tweenEasing":0,"x":-0.3,"y":-4.63},{"duration":2,"tweenEasing":0,"x":0.27,"y":4.13},{"duration":2,"tweenEasing":0,"x":-0.3,"y":-4.63},{"duration":2,"tweenEasing":0,"x":0.27,"y":4.13},{"duration":2,"tweenEasing":0,"x":-0.3,"y":-4.63},{"duration":2,"tweenEasing":0,"x":0.27,"y":4.13},{"duration":2,"tweenEasing":0,"x":-0.3,"y":-4.63},{"duration":2,"tweenEasing":0,"x":0.27,"y":4.13},{"duration":2,"tweenEasing":0,"x":-0.3,"y":-4.63},{"duration":3,"tweenEasing":0,"x":0.27,"y":4.13},{"duration":18}],"scaleFrame":[{"duration":60},{"duration":3,"tweenEasing":0},{"duration":22,"tweenEasing":0,"y":0.95},{"duration":3,"tweenEasing":0,"y":0.95},{"duration":18}]},{"name":"blush","translateFrame":[{"duration":60},{"duration":3,"tweenEasing":0},{"duration":2,"tweenEasing":0,"x":-0.3,"y":-4.63},{"duration":2,"tweenEasing":0,"x":0.27,"y":4.13},{"duration":2,"tweenEasing":0,"x":-0.3,"y":-4.63},{"duration":2,"tweenEasing":0,"x":0.27,"y":4.13},{"duration":2,"tweenEasing":0,"x":-0.3,"y":-4.63},{"duration":2,"tweenEasing":0,"x":0.27,"y":4.13},{"duration":2,"tweenEasing":0,"x":-0.3,"y":-4.63},{"duration":2,"tweenEasing":0,"x":0.27,"y":4.13},{"duration":2,"tweenEasing":0,"x":-0.3,"y":-4.63},{"duration":2,"tweenEasing":0,"x":0.27,"y":4.13},{"duration":2,"tweenEasing":0,"x":-0.3,"y":-4.63},{"duration":3,"tweenEasing":0,"x":0.27,"y":4.13},{"duration":18}],"scaleFrame":[{"duration":60},{"duration":3,"tweenEasing":0},{"duration":22,"tweenEasing":0,"y":0.95},{"duration":3,"tweenEasing":0,"y":0.95},{"duration":18}]},{"name":"spray_2","translateFrame":[{"duration":61},{"duration":2,"tweenEasing":0},{"duration":25,"tweenEasing":0,"x":-1.71},{"duration":4,"tweenEasing":0,"x":-1.71},{"duration":14}]},{"name":"leaf_2","rotateFrame":[{"duration":41},{"duration":8,"tweenEasing":0},{"duration":23,"tweenEasing":0,"rotate":4},{"duration":10,"tweenEasing":0,"rotate":4},{"duration":24}]},{"name":"eye","translateFrame":[{"duration":60},{"duration":3,"tweenEasing":0},{"duration":2,"tweenEasing":0,"x":-0.3,"y":-4.63},{"duration":2,"tweenEasing":0,"x":0.27,"y":4.13},{"duration":2,"tweenEasing":0,"x":-0.3,"y":-4.63},{"duration":2,"tweenEasing":0,"x":0.27,"y":4.13},{"duration":2,"tweenEasing":0,"x":-0.3,"y":-4.63},{"duration":2,"tweenEasing":0,"x":0.27,"y":4.13},{"duration":2,"tweenEasing":0,"x":-0.3,"y":-4.63},{"duration":2,"tweenEasing":0,"x":0.27,"y":4.13},{"duration":2,"tweenEasing":0,"x":-0.3,"y":-4.63},{"duration":2,"tweenEasing":0,"x":0.27,"y":4.13},{"duration":2,"tweenEasing":0,"x":-0.3,"y":-4.63},{"duration":3,"tweenEasing":0,"x":0.27,"y":4.13},{"duration":18}],"scaleFrame":[{"duration":60},{"duration":3,"tweenEasing":0},{"duration":22,"tweenEasing":0,"y":0.95},{"duration":3,"tweenEasing":0,"y":0.95},{"duration":18}]},{"name":"leaf_1","rotateFrame":[{"duration":41},{"duration":8,"tweenEasing":0},{"duration":23,"tweenEasing":0,"rotate":-2},{"duration":10,"tweenEasing":0,"rotate":-2},{"duration":24}]},{"name":"hair_1","translateFrame":[{"duration":24},{"duration":7,"tweenEasing":0},{"tweenEasing":0,"x":15.87,"y":-40.75},{"duration":74}],"rotateFrame":[{"duration":4,"tweenEasing":0},{"duration":4,"tweenEasing":0,"rotate":2},{"duration":4,"tweenEasing":0,"rotate":-12},{"duration":4,"tweenEasing":0,"rotate":2},{"duration":4,"tweenEasing":0,"rotate":-12},{"duration":4,"tweenEasing":0,"rotate":2},{"duration":7,"tweenEasing":0,"rotate":-12},{"duration":36,"tweenEasing":0,"rotate":-53},{"duration":2,"tweenEasing":0},{"duration":2,"tweenEasing":0,"rotate":-12},{"duration":2,"tweenEasing":0,"rotate":2},{"duration":2,"tweenEasing":0,"rotate":-12},{"duration":2,"tweenEasing":0,"rotate":2},{"duration":2,"tweenEasing":0,"rotate":-12},{"duration":2,"tweenEasing":0,"rotate":2},{"duration":2,"tweenEasing":0,"rotate":-12},{"duration":2,"tweenEasing":0,"rotate":2},{"duration":2,"tweenEasing":0,"rotate":-12},{"duration":3,"tweenEasing":0,"rotate":2},{"duration":4,"tweenEasing":0,"rotate":2},{"duration":4,"tweenEasing":0,"rotate":-12},{"duration":4,"tweenEasing":0,"rotate":2},{"duration":4,"tweenEasing":0,"rotate":-12},{"duration":0}],"scaleFrame":[{"duration":24},{"duration":7,"tweenEasing":0},{"tweenEasing":0,"x":1.15,"y":1.15},{"duration":35,"tweenEasing":0,"x":0.01,"y":0.01},{"duration":16,"tweenEasing":0,"x":0.01,"y":0.01},{"duration":23}]},{"name":"hair_3","translateFrame":[{"duration":24},{"duration":7,"tweenEasing":0},{"tweenEasing":0,"x":18.96,"y":-34.07},{"duration":74}],"rotateFrame":[{"duration":4,"tweenEasing":0},{"duration":4,"tweenEasing":0,"rotate":-18},{"duration":4,"tweenEasing":0,"rotate":1},{"duration":4,"tweenEasing":0,"rotate":-18},{"duration":4,"tweenEasing":0,"rotate":1},{"duration":4,"tweenEasing":0,"rotate":-18},{"duration":7,"tweenEasing":0,"rotate":1},{"duration":36,"tweenEasing":0,"rotate":-44},{"duration":2,"tweenEasing":0},{"duration":2,"tweenEasing":0,"rotate":-18},{"duration":2,"tweenEasing":0,"rotate":1},{"duration":2,"tweenEasing":0,"rotate":-18},{"duration":2,"tweenEasing":0,"rotate":1},{"duration":2,"tweenEasing":0,"rotate":-18},{"duration":2,"tweenEasing":0,"rotate":1},{"duration":2,"tweenEasing":0,"rotate":-18},{"duration":2,"tweenEasing":0,"rotate":1},{"duration":2,"tweenEasing":0,"rotate":-18},{"duration":3,"tweenEasing":0,"rotate":1},{"duration":4,"tweenEasing":0,"rotate":-18},{"duration":4,"tweenEasing":0,"rotate":1},{"duration":4,"tweenEasing":0,"rotate":-18},{"duration":4,"tweenEasing":0,"rotate":1},{"duration":0}],"scaleFrame":[{"duration":24},{"duration":7,"tweenEasing":0},{"tweenEasing":0,"x":1.15,"y":1.15},{"duration":35,"tweenEasing":0,"x":0.01,"y":0.01},{"duration":16,"tweenEasing":0,"x":0.01,"y":0.01},{"duration":23}]},{"name":"spray_0","scaleFrame":[{"duration":61},{"duration":2,"tweenEasing":0},{"duration":2,"tweenEasing":0,"x":55,"y":50},{"duration":2,"tweenEasing":0,"x":70,"y":50},{"duration":2,"tweenEasing":0,"x":55,"y":50},{"duration":2,"tweenEasing":0,"x":70,"y":50},{"duration":2,"tweenEasing":0,"x":55,"y":50},{"duration":2,"tweenEasing":0,"x":70,"y":50},{"duration":2,"tweenEasing":0,"x":55,"y":50},{"duration":2,"tweenEasing":0,"x":70,"y":50},{"duration":2,"tweenEasing":0,"x":55,"y":50},{"duration":2,"tweenEasing":0,"x":70,"y":50},{"duration":2,"tweenEasing":0,"x":55,"y":50},{"duration":3,"tweenEasing":0,"x":70,"y":50},{"duration":18}]},{"name":"L","rotateFrame":[{"duration":31},{"duration":16,"tweenEasing":0},{"duration":36,"rotate":-53},{"duration":16,"tweenEasing":0},{"duration":7,"rotate":-53}],"scaleFrame":[{"duration":31},{"duration":16,"tweenEasing":0},{"duration":36,"x":100,"y":100},{"duration":16,"tweenEasing":0},{"duration":7,"x":100,"y":100}]},{"name":"L1","translateFrame":[{"duration":38},{"duration":68,"x":-28.41,"y":13.94}],"rotateFrame":[{"duration":38},{"duration":16,"tweenEasing":0},{"duration":36,"rotate":-53},{"duration":16,"tweenEasing":0},{"duration":0,"rotate":-53}],"scaleFrame":[{"duration":38},{"duration":16,"tweenEasing":0},{"duration":36,"x":100,"y":100},{"duration":16,"tweenEasing":0},{"duration":0,"x":100,"y":100}]}],"slot":[{"name":"body_1","displayFrame":[{"duration":41},{"duration":19,"value":1},{"duration":46}]},{"name":"mouth","displayFrame":[{"duration":41},{"duration":19,"value":2},{"duration":36,"value":1},{"duration":10}]},{"name":"eye","displayFrame":[{"duration":41},{"duration":19,"value":2},{"duration":36,"value":1},{"duration":10}]},{"name":"hair_3","colorFrame":[{"duration":28},{"duration":3,"tweenEasing":0},{"duration":35,"tweenEasing":0,"value":{"aM":0}},{"tweenEasing":0,"value":{"aM":0}},{"duration":39}]},{"name":"hair_2","colorFrame":[{"duration":28},{"duration":3,"tweenEasing":0},{"duration":35,"tweenEasing":0,"value":{"aM":0}},{"tweenEasing":0,"value":{"aM":0}},{"duration":39}]},{"name":"hair_1","colorFrame":[{"duration":28},{"duration":3,"tweenEasing":0},{"duration":35,"tweenEasing":0,"value":{"aM":0}},{"tweenEasing":0,"value":{"aM":0}},{"duration":39}]},{"name":"spray_0","displayFrame":[{"duration":88},{"duration":18,"value":-1}]},{"name":"spray_2","colorFrame":[{"duration":52,"tweenEasing":0,"value":{"aM":0}},{"duration":9,"tweenEasing":0,"value":{"aM":0}},{"duration":36,"tweenEasing":0},{"duration":9,"value":{"aM":0}}]},{"name":"spray_1","colorFrame":[{"duration":52,"tweenEasing":0,"value":{"aM":0}},{"duration":9,"tweenEasing":0,"value":{"aM":0}},{"duration":31,"tweenEasing":0},{"duration":5,"tweenEasing":0},{"duration":9,"value":{"aM":0}}]},{"name":"L","colorFrame":[{"duration":36},{"duration":11,"tweenEasing":0},{"duration":41,"value":{"aM":0}},{"duration":11,"tweenEasing":0},{"duration":7,"value":{"aM":0}}]},{"name":"L1","colorFrame":[{"duration":43},{"duration":11,"tweenEasing":0},{"duration":41,"value":{"aM":0}},{"duration":11,"tweenEasing":0},{"duration":0,"value":{"aM":0}}]}]},{"duration":45,"playTimes":0,"name":"shake","bone":[{"name":"body","translateFrame":[{"duration":3,"tweenEasing":0},{"duration":36,"tweenEasing":0,"y":-4.33},{"duration":6,"tweenEasing":0,"y":-4.33},{"duration":0}],"scaleFrame":[{"duration":9},{"duration":3,"tweenEasing":0},{"duration":22,"tweenEasing":0,"y":0.95},{"duration":3,"tweenEasing":0,"y":0.95},{"duration":8}]},{"name":"exclamation","translateFrame":[{"duration":11,"tweenEasing":0},{"duration":34,"x":1.61,"y":-9.49}],"rotateFrame":[{"duration":11,"tweenEasing":0},{"duration":34,"rotate":-110}]},{"name":"blush","translateFrame":[{"duration":9,"tweenEasing":0},{"duration":3,"tweenEasing":0},{"duration":2,"tweenEasing":0,"x":-0.3,"y":-4.63},{"duration":2,"tweenEasing":0,"x":0.27,"y":4.13},{"duration":2,"tweenEasing":0,"x":-0.3,"y":-4.63},{"duration":2,"tweenEasing":0,"x":0.27,"y":4.13},{"duration":2,"tweenEasing":0,"x":-0.3,"y":-4.63},{"duration":2,"tweenEasing":0,"x":0.27,"y":4.13},{"duration":2,"tweenEasing":0,"x":-0.3,"y":-4.63},{"duration":2,"tweenEasing":0,"x":0.27,"y":4.13},{"duration":2,"tweenEasing":0,"x":-0.3,"y":-4.63},{"duration":2,"tweenEasing":0,"x":0.27,"y":4.13},{"duration":2,"tweenEasing":0,"x":-0.3,"y":-4.63},{"duration":3,"tweenEasing":0,"x":0.27,"y":4.13},{"duration":8}],"scaleFrame":[{"duration":9},{"duration":3,"tweenEasing":0},{"duration":22,"tweenEasing":0,"y":0.95},{"duration":3,"tweenEasing":0,"y":0.95},{"duration":8}]},{"name":"hair_2","rotateFrame":[{"duration":9},{"duration":3,"tweenEasing":0},{"duration":2,"tweenEasing":0,"rotate":-17},{"duration":2,"tweenEasing":0,"rotate":-2},{"duration":2,"tweenEasing":0,"rotate":-17},{"duration":2,"tweenEasing":0,"rotate":-2},{"duration":2,"tweenEasing":0,"rotate":-17},{"duration":2,"tweenEasing":0,"rotate":-2},{"duration":2,"tweenEasing":0,"rotate":-17},{"duration":2,"tweenEasing":0,"rotate":-2},{"duration":2,"tweenEasing":0,"rotate":-17},{"duration":2,"tweenEasing":0,"rotate":-2},{"duration":2,"tweenEasing":0,"rotate":-17},{"duration":3,"tweenEasing":0,"rotate":-2},{"duration":8}]},{"name":"mouth","translateFrame":[{"duration":9,"tweenEasing":0},{"duration":3,"tweenEasing":0},{"duration":2,"tweenEasing":0,"x":-0.3,"y":-4.63},{"duration":2,"tweenEasing":0,"x":0.27,"y":4.13},{"duration":2,"tweenEasing":0,"x":-0.3,"y":-4.63},{"duration":2,"tweenEasing":0,"x":0.27,"y":4.13},{"duration":2,"tweenEasing":0,"x":-0.3,"y":-4.63},{"duration":2,"tweenEasing":0,"x":0.27,"y":4.13},{"duration":2,"tweenEasing":0,"x":-0.3,"y":-4.63},{"duration":2,"tweenEasing":0,"x":0.27,"y":4.13},{"duration":2,"tweenEasing":0,"x":-0.3,"y":-4.63},{"duration":2,"tweenEasing":0,"x":0.27,"y":4.13},{"duration":2,"tweenEasing":0,"x":-0.3,"y":-4.63},{"duration":3,"tweenEasing":0,"x":0.27,"y":4.13},{"duration":8}],"scaleFrame":[{"duration":9},{"duration":3,"tweenEasing":0},{"duration":22,"tweenEasing":0,"y":0.95},{"duration":3,"tweenEasing":0,"y":0.95},{"duration":8}]},{"name":"eye","translateFrame":[{"duration":9,"tweenEasing":0},{"duration":3,"tweenEasing":0},{"duration":2,"tweenEasing":0,"x":-0.3,"y":-4.63},{"duration":2,"tweenEasing":0,"x":0.27,"y":4.13},{"duration":2,"tweenEasing":0,"x":-0.3,"y":-4.63},{"duration":2,"tweenEasing":0,"x":0.27,"y":4.13},{"duration":2,"tweenEasing":0,"x":-0.3,"y":-4.63},{"duration":2,"tweenEasing":0,"x":0.27,"y":4.13},{"duration":2,"tweenEasing":0,"x":-0.3,"y":-4.63},{"duration":2,"tweenEasing":0,"x":0.27,"y":4.13},{"duration":2,"tweenEasing":0,"x":-0.3,"y":-4.63},{"duration":2,"tweenEasing":0,"x":0.27,"y":4.13},{"duration":2,"tweenEasing":0,"x":-0.3,"y":-4.63},{"duration":3,"tweenEasing":0,"x":0.27,"y":4.13},{"duration":8}],"scaleFrame":[{"duration":9},{"duration":3,"tweenEasing":0},{"duration":22,"tweenEasing":0,"y":0.95},{"duration":3,"tweenEasing":0,"y":0.95},{"duration":8}]},{"name":"leaf_1","rotateFrame":[{"duration":9},{"duration":3,"tweenEasing":0},{"duration":2,"tweenEasing":0,"rotate":-3},{"duration":2,"tweenEasing":0,"rotate":3},{"duration":2,"tweenEasing":0,"rotate":-3},{"duration":2,"tweenEasing":0,"rotate":3},{"duration":2,"tweenEasing":0,"rotate":-3},{"duration":2,"tweenEasing":0,"rotate":3},{"duration":2,"tweenEasing":0,"rotate":-3},{"duration":2,"tweenEasing":0,"rotate":3},{"duration":2,"tweenEasing":0,"rotate":-3},{"duration":2,"tweenEasing":0,"rotate":3},{"duration":2,"tweenEasing":0,"rotate":-3},{"duration":3,"tweenEasing":0,"rotate":3},{"duration":8}]},{"name":"hair_1","rotateFrame":[{"duration":9},{"duration":3,"tweenEasing":0},{"duration":2,"tweenEasing":0,"rotate":-12},{"duration":2,"tweenEasing":0,"rotate":2},{"duration":2,"tweenEasing":0,"rotate":-12},{"duration":2,"tweenEasing":0,"rotate":2},{"duration":2,"tweenEasing":0,"rotate":-12},{"duration":2,"tweenEasing":0,"rotate":2},{"duration":2,"tweenEasing":0,"rotate":-12},{"duration":2,"tweenEasing":0,"rotate":2},{"duration":2,"tweenEasing":0,"rotate":-12},{"duration":2,"tweenEasing":0,"rotate":2},{"duration":2,"tweenEasing":0,"rotate":-12},{"duration":3,"tweenEasing":0,"rotate":2},{"duration":8}]},{"name":"hair_3","rotateFrame":[{"duration":9},{"duration":3,"tweenEasing":0},{"duration":2,"tweenEasing":0,"rotate":-18},{"duration":2,"tweenEasing":0,"rotate":1},{"duration":2,"tweenEasing":0,"rotate":-18},{"duration":2,"tweenEasing":0,"rotate":1},{"duration":2,"tweenEasing":0,"rotate":-18},{"duration":2,"tweenEasing":0,"rotate":1},{"duration":2,"tweenEasing":0,"rotate":-18},{"duration":2,"tweenEasing":0,"rotate":1},{"duration":2,"tweenEasing":0,"rotate":-18},{"duration":2,"tweenEasing":0,"rotate":1},{"duration":2,"tweenEasing":0,"rotate":-18},{"duration":3,"tweenEasing":0,"rotate":1},{"duration":8}]},{"name":"leaf_2","rotateFrame":[{"duration":9},{"duration":3,"tweenEasing":0},{"duration":2,"tweenEasing":0,"rotate":3},{"duration":2,"tweenEasing":0,"rotate":-2},{"duration":2,"tweenEasing":0,"rotate":3},{"duration":2,"tweenEasing":0,"rotate":-2},{"duration":2,"tweenEasing":0,"rotate":3},{"duration":2,"tweenEasing":0,"rotate":-2},{"duration":2,"tweenEasing":0,"rotate":3},{"duration":2,"tweenEasing":0,"rotate":-2},{"duration":2,"tweenEasing":0,"rotate":3},{"duration":2,"tweenEasing":0,"rotate":-2},{"duration":2,"tweenEasing":0,"rotate":3},{"duration":3,"tweenEasing":0,"rotate":-2},{"duration":8}]}],"slot":[{"name":"mouth","displayFrame":[{"duration":3},{"duration":39,"value":1},{"duration":3}]},{"name":"eye","displayFrame":[{"duration":3},{"duration":39,"value":1},{"duration":3}]},{"name":"exclamation","colorFrame":[{"duration":3,"tweenEasing":0,"value":{"aM":0}},{"duration":7,"tweenEasing":0},{"duration":5,"tweenEasing":0},{"duration":30,"value":{"aM":0}}]}]},{"duration":6,"playTimes":0,"name":"up","bone":[{"name":"body","scaleFrame":[{"duration":2},{"duration":4,"tweenEasing":0},{"duration":0,"x":0.95}]},{"name":"hair_2","rotateFrame":[{"duration":2},{"duration":4,"tweenEasing":0},{"duration":0,"rotate":30}]},{"name":"mouth","translateFrame":[{"duration":2},{"duration":4,"tweenEasing":0},{"duration":0,"x":-4.83,"y":0.32}]},{"name":"blush","translateFrame":[{"duration":2},{"duration":4,"tweenEasing":0},{"duration":0,"x":-4.83,"y":0.32}]},{"name":"leaf_2","rotateFrame":[{"duration":2},{"duration":4,"tweenEasing":0},{"duration":0,"rotate":2}]},{"name":"eye","translateFrame":[{"duration":2},{"duration":4,"tweenEasing":0},{"duration":0,"x":-4.83,"y":0.32}]},{"name":"leaf_1","rotateFrame":[{"duration":2},{"duration":4,"tweenEasing":0},{"duration":0,"rotate":-4}]},{"name":"hair_1","rotateFrame":[{"duration":2},{"duration":4,"tweenEasing":0},{"duration":0,"rotate":14}]},{"name":"hair_3","rotateFrame":[{"duration":2},{"duration":4,"tweenEasing":0},{"duration":0,"rotate":24}]}],"slot":[{"name":"mouth","displayFrame":[{"duration":6,"value":2}]},{"name":"eye","displayFrame":[{"duration":6,"value":2}]}]},{"duration":6,"playTimes":0,"name":"down","bone":[{"name":"body","scaleFrame":[{"duration":2},{"duration":4,"tweenEasing":0},{"duration":0,"x":1.03}]},{"name":"hair_2","rotateFrame":[{"duration":2},{"duration":4,"tweenEasing":0},{"duration":0,"rotate":-14}]},{"name":"mouth","translateFrame":[{"duration":2},{"duration":4,"tweenEasing":0},{"duration":0,"x":5.92,"y":-0.39}]},{"name":"blush","translateFrame":[{"duration":2},{"duration":4,"tweenEasing":0},{"duration":0,"x":5.92,"y":-0.39}]},{"name":"leaf_2","rotateFrame":[{"duration":2},{"duration":4,"tweenEasing":0},{"duration":0,"rotate":-3}]},{"name":"eye","translateFrame":[{"duration":2},{"duration":4,"tweenEasing":0},{"duration":0,"x":5.92,"y":-0.39}]},{"name":"leaf_1","rotateFrame":[{"duration":2},{"duration":4,"tweenEasing":0},{"duration":0,"rotate":3}]},{"name":"hair_1","rotateFrame":[{"duration":2},{"duration":4,"tweenEasing":0},{"duration":0,"rotate":-17}]},{"name":"hair_3","rotateFrame":[{"duration":2},{"duration":4,"tweenEasing":0},{"duration":0,"rotate":-25}]}],"slot":[{"name":"mouth","displayFrame":[{"duration":6,"value":2}]},{"name":"eye","displayFrame":[{"duration":6,"value":2}]}]},{"duration":6,"playTimes":0,"name":"left","bone":[{"name":"body","scaleFrame":[{"duration":2},{"duration":4,"tweenEasing":0},{"duration":0,"y":0.95}]},{"name":"hair_2","rotateFrame":[{"duration":2},{"duration":4,"tweenEasing":0},{"duration":0,"rotate":21}]},{"name":"mouth","translateFrame":[{"duration":2},{"duration":4,"tweenEasing":0},{"duration":0,"x":-0.36,"y":-5.44}]},{"name":"blush","translateFrame":[{"duration":2},{"duration":4,"tweenEasing":0},{"duration":0,"x":-0.36,"y":-5.44}]},{"name":"leaf_2","rotateFrame":[{"duration":2},{"duration":4,"tweenEasing":0},{"duration":0,"rotate":4}]},{"name":"eye","translateFrame":[{"duration":2},{"duration":4,"tweenEasing":0},{"duration":0,"x":-0.36,"y":-5.44}]},{"name":"leaf_1","rotateFrame":[{"duration":2},{"duration":4,"tweenEasing":0},{"duration":0,"rotate":2}]},{"name":"hair_1","rotateFrame":[{"duration":2},{"duration":4,"tweenEasing":0},{"duration":0,"rotate":21}]},{"name":"hair_3","rotateFrame":[{"duration":2},{"duration":4,"tweenEasing":0},{"duration":0,"rotate":25}]}],"slot":[{"name":"mouth","displayFrame":[{"duration":6,"value":2}]},{"name":"eye","displayFrame":[{"duration":6,"value":2}]}]},{"duration":6,"playTimes":0,"name":"right","bone":[{"name":"body","scaleFrame":[{"duration":2},{"duration":4,"tweenEasing":0},{"duration":0,"y":0.95}]},{"name":"hair_2","rotateFrame":[{"duration":2},{"duration":4,"tweenEasing":0},{"duration":0,"rotate":-20}]},{"name":"mouth","translateFrame":[{"duration":2},{"duration":4,"tweenEasing":0},{"duration":0,"x":0.27,"y":4.06}]},{"name":"blush","translateFrame":[{"duration":2},{"duration":4,"tweenEasing":0},{"duration":0,"x":0.27,"y":4.06}]},{"name":"leaf_2","rotateFrame":[{"duration":2},{"duration":4,"tweenEasing":0},{"duration":0,"rotate":-3}]},{"name":"eye","translateFrame":[{"duration":2},{"duration":4,"tweenEasing":0},{"duration":0,"x":0.27,"y":4.06}]},{"name":"leaf_1","rotateFrame":[{"duration":2},{"duration":4,"tweenEasing":0},{"duration":0,"rotate":-5}]},{"name":"hair_1","rotateFrame":[{"duration":2},{"duration":4,"tweenEasing":0},{"duration":0,"rotate":-26}]},{"name":"hair_3","rotateFrame":[{"duration":2},{"duration":4,"tweenEasing":0},{"duration":0,"rotate":-17}]}],"slot":[{"name":"mouth","displayFrame":[{"duration":6,"value":2}]},{"name":"eye","displayFrame":[{"duration":6,"value":2}]}]}],"defaultActions":[{"gotoAndPlay":"click"}]}]}