[
	{
		"blockName": "zongzi",
		"style": "2,2"
	},
	{
		"blockName": "corn",
		"style": "2,1"
	},
	{
		"blockName": "bun",
		"style": "1,2"
	},
	{
		"blockName": "dumpling",
		"style": "1,1"
	},
	{
		"blockName": "orange",
		"style": "1,1"
	},
	{
		"blockName": "peach",
		"style": "1,1"
	},
	{
		"blockName": "apple",
		"style": "1,1"
	},
	{
		"blockName": "avocado",
		"style": "1,1"
	},
	{
		"blockName": "chips",
		"style": "2,2"
	},
	{
		"blockName": "Croissant",
		"style": "1,2"
	},
	{
		"blockName": "eggplant",
		"style": "2,1"
	},
	{
		"blockName": "EggRoll",
		"style": "1,2"
	},
	{
		"blockName": "Fishball",
		"style": "2,1"
	},
	{
		"blockName": "Icecream",
		"style": "2,1"
	},
	{
		"blockName": "MatchaCake",
		"style": "1,2"
	},
	{
		"blockName": "milk",
		"style": "2,1"
	},
	{
		"blockName": "milkytea",
		"style": "2,1"
	},
	{
		"blockName": "peas",
		"style": "1,2"
	},
	{
		"blockName": "Pudding",
		"style": "2,1"
	},
	{
		"blockName": "sausage",
		"style": "1,2"
	},
	{
		"blockName": "sushi",
		"style": "1,2"
	},
	{
		"blockName": "toast",
		"style": "2,2"
	},
	{
		"blockName": "FriedEggs",
		"style": "2,2"
	}
]
